iddb/__init__.py
iddb/about.py
iddb/cmd.py
iddb/cmd_processor.py
iddb/cmd_router.py
iddb/cmd_tracker.py
iddb/config.py
iddb/const.py
iddb/counter.py
iddb/data_struct.py
iddb/event_loop.py
iddb/gdb_controller.py
iddb/gdb_manager.py
iddb/gdb_session.py
iddb/gdbparser.py
iddb/gdbserver_starter.py
iddb/global_handler.py
iddb/logging.py
iddb/main.py
iddb/mi_formatter.py
iddb/mtracer.py
iddb/port_mgr.py
iddb/response_processor.py
iddb/response_transformer.py
iddb/service_mgr.py
iddb/startup.py
iddb/state_manager.py
iddb/status_server.py
iddb/utils.py
iddb/conf/mosquitto.conf
iddb/gdb_ext/noobextension.py
iddb/gdb_ext/runtime-gdb-grpc.py
iddb/gdb_ext/runtime-gdb.py
iddb-0.0.1.dev1.dist-info/METADATA
iddb-0.0.1.dev1.dist-info/WHEEL
iddb-0.0.1.dev1.dist-info/entry_points.txt
iddb-0.0.1.dev1.dist-info/RECORD
